StellarPolAnalyzer/__init__.py
StellarPolAnalyzer/alignment.py
StellarPolAnalyzer/astrometry.py
StellarPolAnalyzer/detection.py
StellarPolAnalyzer/pairing.py
StellarPolAnalyzer/photometry.py
StellarPolAnalyzer/pipeline.py
StellarPolAnalyzer/report.py
StellarPolAnalyzer/utils.py
StellarPolAnalyzer/visualization.py
stellarpolanalyzer-0.1.19.dist-info/licenses/LICENSE
stellarpolanalyzer-0.1.19.dist-info/METADATA
stellarpolanalyzer-0.1.19.dist-info/WHEEL
stellarpolanalyzer-0.1.19.dist-info/top_level.txt
stellarpolanalyzer-0.1.19.dist-info/RECORD
