Metadata-Version: 2.4
Name: StellarPolAnalyzer
Version: 0.1.19
Summary: Librería Python que automatiza un completo un pipeline polarimétrico sobre imágenes FITS astronómicas: Empareja, fotometriza y astrometriza imágenes polarimétricas de campo estelar en un solo flujo.
Home-page: https://github.com/oscarmellizo/StellarPolAnalyzer
Author: Oscar Mellizo Angulo
Author-email: omellizo@gmail.com
License: Apache License 2.0
Classifier: Programming Language :: Python :: 3
Classifier: License :: OSI Approved :: Apache Software License
Classifier: Operating System :: OS Independent
License-File: LICENSE
Requires-Dist: numpy
Requires-Dist: matplotlib
Requires-Dist: astropy
Requires-Dist: photutils
Requires-Dist: scikit-learn
Requires-Dist: scikit-image
Requires-Dist: scipy
Requires-Dist: astroquery
Requires-Dist: reportlab
Dynamic: author
Dynamic: author-email
Dynamic: classifier
Dynamic: description
Dynamic: description-content-type
Dynamic: home-page
Dynamic: license
Dynamic: license-file
Dynamic: requires-dist
Dynamic: summary
